rangefilter/__init__.py
rangefilter/apps.py
rangefilter/filters.py
rangefilter/models.py
rangefilter/locale/cs_CZ/LC_MESSAGES/django.mo
rangefilter/locale/cs_CZ/LC_MESSAGES/django.po
rangefilter/locale/da/LC_MESSAGES/django.mo
rangefilter/locale/da/LC_MESSAGES/django.po
rangefilter/locale/de/LC_MESSAGES/django.mo
rangefilter/locale/de/LC_MESSAGES/django.po
rangefilter/locale/el/LC_MESSAGES/django.mo
rangefilter/locale/el/LC_MESSAGES/django.po
rangefilter/locale/en_US/LC_MESSAGES/django.mo
rangefilter/locale/en_US/LC_MESSAGES/django.po
rangefilter/locale/es/LC_MESSAGES/django.mo
rangefilter/locale/es/LC_MESSAGES/django.po
rangefilter/locale/es_AR/LC_MESSAGES/django.mo
rangefilter/locale/es_AR/LC_MESSAGES/django.po
rangefilter/locale/fa/LC_MESSAGES/django.mo
rangefilter/locale/fa/LC_MESSAGES/django.po
rangefilter/locale/fr/LC_MESSAGES/django.mo
rangefilter/locale/fr/LC_MESSAGES/django.po
rangefilter/locale/it/LC_MESSAGES/django.mo
rangefilter/locale/it/LC_MESSAGES/django.po
rangefilter/locale/ja/LC_MESSAGES/django.mo
rangefilter/locale/ja/LC_MESSAGES/django.po
rangefilter/locale/pl/LC_MESSAGES/django.mo
rangefilter/locale/pl/LC_MESSAGES/django.po
rangefilter/locale/pt_BR/LC_MESSAGES/django.mo
rangefilter/locale/pt_BR/LC_MESSAGES/django.po
rangefilter/locale/pt_PT/LC_MESSAGES/django.mo
rangefilter/locale/pt_PT/LC_MESSAGES/django.po
rangefilter/locale/ru/LC_MESSAGES/django.mo
rangefilter/locale/ru/LC_MESSAGES/django.po
rangefilter/locale/tr/LC_MESSAGES/django.mo
rangefilter/locale/tr/LC_MESSAGES/django.po
rangefilter/locale/uk/LC_MESSAGES/django.mo
rangefilter/locale/uk/LC_MESSAGES/django.po
rangefilter/locale/zh_CN/LC_MESSAGES/django.mo
rangefilter/locale/zh_CN/LC_MESSAGES/django.po
rangefilter/locale/zh_Hans/LC_MESSAGES/django.mo
rangefilter/locale/zh_Hans/LC_MESSAGES/django.po
rangefilter/templates/rangefilter/date_filter.html
rangefilter/templates/rangefilter/date_filter_1_8.html
rangefilter/templates/rangefilter/date_range_quick_select_list_filter.html
django_admin_rangefilter-0.12.5.dist-info/LICENSE
django_admin_rangefilter-0.12.5.dist-info/METADATA
django_admin_rangefilter-0.12.5.dist-info/WHEEL
django_admin_rangefilter-0.12.5.dist-info/top_level.txt
django_admin_rangefilter-0.12.5.dist-info/RECORD
